auto_rest/__init__.py
auto_rest/filters.py
auto_rest/introspection.py
auto_rest/openapi.py
auto_rest/pagination.py
auto_rest/routers.py
auto_rest/serializers.py
auto_rest/viewsets.py
drf_auto_rest-1.0.2.dist-info/WHEEL
drf_auto_rest-1.0.2.dist-info/METADATA
drf_auto_rest-1.0.2.dist-info/RECORD
