Metadata-Version: 2.3
Name: drf-auto-rest
Version: 1.0.2
Summary: PostgREST-like automatic REST API generation for Django REST Framework
Requires-Dist: django>=4.2.0
Requires-Dist: djangorestframework>=3.14.0
Requires-Dist: drf-spectacular>=0.27.0
Requires-Python: >=3.10
